itrails/__init__.py
itrails/_version.py
itrails/combine_states.py
itrails/cutpoints.py
itrails/deepest_ti.py
itrails/expm.py
itrails/get_emission_prob_mat.py
itrails/get_joint_prob_mat.py
itrails/get_tab.py
itrails/get_trans_emiss.py
itrails/helper_omegas.py
itrails/int_combine_states.py
itrails/int_get_emission_prob_mat.py
itrails/int_get_joint_prob_mat.py
itrails/int_get_ordered.py
itrails/int_get_tab.py
itrails/int_get_times.py
itrails/int_get_trans_emiss.py
itrails/int_load_trans_mat.py
itrails/int_optimizer.py
itrails/int_shared_data.py
itrails/int_vanloan.py
itrails/ncpu.py
itrails/optimizer.py
itrails/read_data.py
itrails/run_markov_chain_AB.py
itrails/run_markov_chain_ABC.py
itrails/trans_mat.py
itrails/vanloan.py
itrails/workflow_int_optimize.py
itrails/workflow_int_posterior.py
itrails/workflow_int_viterbi.py
itrails/workflow_optimize.py
itrails/workflow_posterior.py
itrails/workflow_viterbi.py
itrails/yaml_helpers.py
itrails/data/trans_mat_full_1.csv
itrails/data/trans_mat_full_2.csv
itrails/data/trans_mat_full_3.csv
itrails/examples/example_config.yaml
itrails/examples/example_config_int.yaml
itrails-2.0.3.dist-info/licenses/LICENSE
itrails-2.0.3.dist-info/METADATA
itrails-2.0.3.dist-info/WHEEL
itrails-2.0.3.dist-info/entry_points.txt
itrails-2.0.3.dist-info/top_level.txt
itrails-2.0.3.dist-info/RECORD
