Metadata-Version: 2.4
Name: itrails
Version: 2.0.3
Summary: Tree reconstruction of ancestry using incomplete lineage sorting
Author-email: Iker Rivas-González <iker_rivas_gonzalez@eva.mpg.de>, David Martin-Pestana <dmape@birc.au.dk>
Maintainer-email: David Martin-Pestana <dmape@birc.au.dk>
License: MIT License
Project-URL: Homepage, https://github.com/trails-phylogeny/itrails
Project-URL: BugTracker, https://github.com/trails-phylogeny/itrails/issues
Requires-Python: >=3.12
License-File: LICENSE
Requires-Dist: numpy==1.26.4
Requires-Dist: scipy==1.13.0
Requires-Dist: joblib==1.4.2
Requires-Dist: numba==0.59.1
Requires-Dist: biopython==1.84
Requires-Dist: pyyaml==6.0.2
Requires-Dist: h5py
Requires-Dist: pandas
Requires-Dist: ray[default]
Provides-Extra: docs
Requires-Dist: sphinx; extra == "docs"
Requires-Dist: furo; extra == "docs"
Requires-Dist: myst-parser; extra == "docs"
Requires-Dist: sphinx-autodoc-typehints; extra == "docs"
Dynamic: license-file
